snakeoil/__init__.py
snakeoil/_fileutils.py
snakeoil/_internals.py
snakeoil/bash.py
snakeoil/caching.py
snakeoil/compatibility.py
snakeoil/constraints.py
snakeoil/containers.py
snakeoil/contexts.py
snakeoil/currying.py
snakeoil/data_source.py
snakeoil/decorators.py
snakeoil/demandload.py
snakeoil/dependant_methods.py
snakeoil/errors.py
snakeoil/fileutils.py
snakeoil/formatters.py
snakeoil/iterables.py
snakeoil/log.py
snakeoil/mappings.py
snakeoil/modules.py
snakeoil/obj.py
snakeoil/python_namespaces.py
snakeoil/sequences.py
snakeoil/stringio.py
snakeoil/strings.py
snakeoil/struct_compat.py
snakeoil/tar.py
snakeoil/version.py
snakeoil/chksum/__init__.py
snakeoil/chksum/defaults.py
snakeoil/cli/__init__.py
snakeoil/cli/arghparse.py
snakeoil/cli/exceptions.py
snakeoil/cli/input.py
snakeoil/cli/tool.py
snakeoil/compression/__init__.py
snakeoil/compression/_bzip2.py
snakeoil/compression/_util.py
snakeoil/compression/_xz.py
snakeoil/delayed/__init__.py
snakeoil/deprecation/__init__.py
snakeoil/deprecation/__main__.py
snakeoil/dist/__init__.py
snakeoil/dist/generate_docs.py
snakeoil/dist/generate_man_rsts.py
snakeoil/dist/sphinxext.py
snakeoil/dist/utilities.py
snakeoil/klass/__init__.py
snakeoil/klass/_deprecated.py
snakeoil/klass/immutable.py
snakeoil/klass/properties.py
snakeoil/klass/util.py
snakeoil/osutils/__init__.py
snakeoil/osutils/mount.py
snakeoil/process/__init__.py
snakeoil/process/namespaces.py
snakeoil/process/spawn.py
snakeoil/test/__init__.py
snakeoil/test/abstract.py
snakeoil/test/argparse_helpers.py
snakeoil/test/code_quality.py
snakeoil/test/eq_hash_inheritance.py
snakeoil/test/mixins.py
snakeoil/test/modules.py
snakeoil/test/slot_shadowing.py
snakeoil/tools/__init__.py
snakeoil/tools/find_unused_exports.py
snakeoil-0.11.0.dist-info/licenses/LICENSE
snakeoil-0.11.0.dist-info/WHEEL
snakeoil-0.11.0.dist-info/METADATA
snakeoil-0.11.0.dist-info/RECORD
