Metadata-Version: 2.4
Name: snakeoil
Version: 0.11.0
Summary: misc common functionality and useful optimizations
Author-email: Tim Harder <radhermit@gmail.com>, Brian Harring <ferringb@gmail.com>, Arthur Zamarin <arthurzam@gentoo.org>
Maintainer-email: Arthur Zamarin <arthurzam@gentoo.org>
Requires-Python: ~=3.11
Classifier: Intended Audience :: Developers
Classifier: License :: OSI Approved :: BSD License
Classifier: Programming Language :: Python :: 3.11
Classifier: Programming Language :: Python :: 3.12
Classifier: Programming Language :: Python :: 3.13
Classifier: Programming Language :: Python :: 3.14
License-File: LICENSE
Requires-Dist: sphinx ; extra == "doc"
Requires-Dist: pytest >=6.0 ; extra == "test"
Requires-Dist: pytest-cov ; extra == "test"
Requires-Dist: pytest-subtests ~= 0.15.0 ; extra == "test"
Requires-Dist: sphinx ; extra == "test"
Project-URL: Documentation, https://pkgcore.github.io/snakeoil/
Project-URL: Homepage, https://github.com/pkgcore/snakeoil
Project-URL: Source, https://github.com/pkgcore/snakeoil
Provides-Extra: doc
Provides-Extra: test
